{"HighlightColour":{"_type":"color","alpha":1,"hex":"#ff6bf1","hsl":{"_type":"hslaColor","a":1,"h":305.6756756756757,"l":0.7098039215686275,"s":1},"hsv":{"_type":"hsvaColor","a":1,"h":305.6756756756757,"s":0.580392156862745,"v":1},"rgb":{"_type":"rgbaColor","a":1,"b":241,"g":107,"r":255}},"_createdAt":"2025-03-26T10:24:50Z","_id":"siteSettings","_rev":"5sDLUEU8cN2szqSFaLLozg","_type":"siteSettings","_updatedAt":"2025-05-27T13:24:37Z","behanceUrl":"https://www.behance.net/alejanddalmau/moodboards","contactEmail":"hi@designbytwist.com","footerContactButtonTitle":["Let's work","Let's go"],"footerContactCtas":["Do you need a Twist?","You’ve made it this far. Might as well say hi.","Do you have a project in mind? We’d love to hear about it."],"instagramUrl":"https://www.instagram.com/designbytwist/","linkedInUrl":"https://www.linkedin.com/company/design-by-twist/","newProjectExitPrompt":"You forgot to click submit. Are you sure?","newsletterCta":"Sign up and stay in the loop. We won’t bother you too much, we promise 😶","officeAddress":"Carrer Lepant 14, 08242 Manresa Barcelona, Spain","officeGoogleMapsLink":"https://www.google.com/maps/place/Carrer+de+Lepant,+14,+08242+Manresa,+Barcelona,+Spain/data=!4m2!3m1!1s0x12a45813cf556381:0x494c1157609b7464?sa=X&ved=1t:242&ictx=111","referenceTitle":"Site Settings"}